testinfra_bdd/__init__.py
testinfra_bdd/address.py
testinfra_bdd/command.py
testinfra_bdd/exception_message.py
testinfra_bdd/file.py
testinfra_bdd/file_helpers.py
testinfra_bdd/fixture.py
testinfra_bdd/given.py
testinfra_bdd/group.py
testinfra_bdd/package.py
testinfra_bdd/parsers.py
testinfra_bdd/pip.py
testinfra_bdd/process.py
testinfra_bdd/service.py
testinfra_bdd/socket.py
testinfra_bdd/user.py
testinfra_bdd/when.py
testinfra_bdd-3.1.1.dist-info/LICENSE
testinfra_bdd-3.1.1.dist-info/METADATA
testinfra_bdd-3.1.1.dist-info/WHEEL
testinfra_bdd-3.1.1.dist-info/top_level.txt
testinfra_bdd-3.1.1.dist-info/RECORD
