Metadata-Version: 2.1
Name: testinfra-bdd
Version: 3.1.1
Summary: An interface between pytest-bdd and pytest-testinfra.
Home-page: https://github.com/cbdq-io/testinfra-bdd
Author: Cloud Based DQ Ltd.
Author-email: info@cbdq.io
Project-URL: Bug Tracker, https://github.com/cbdq-io/testinfra-bdd/issues
Keywords: testinfra,bdd
Classifier: Programming Language :: Python :: 3
Classifier: License :: OSI Approved :: BSD License
Classifier: Operating System :: OS Independent
Requires-Python: >=3.9
License-File: LICENSE
Requires-Dist: jmespath<2.0.0,>=1.0.0
Requires-Dist: pytest-bdd<9.0.0,>=6.0.0
Requires-Dist: pytest-testinfra<11.0.0,>=9.0.0
